backend_flit/__init__.py
backend_flit-0.0.1.dist-info/WHEEL
backend_flit-0.0.1.dist-info/METADATA
backend_flit-0.0.1.dist-info/RECORD
