Metadata-Version: 2.1
Name: backend_flit
Version: 0.0.1
Summary: Backend flit
Author-email: Mohammad Mahfooz Alam <mahfooz.iiitian@gmail.com>
Requires-Python: >=3.11
Classifier: Programming Language :: Python :: 3
Requires-Dist: pytest >=8.2.0 ; extra == "test"
Project-URL: Homepage, https://github.com/pypa/backend_flit
Project-URL: Issues, https://github.com/pypa/backend_flit/issues
Provides-Extra: test
